supermetrics/__init__.py
supermetrics/__version__.py
supermetrics/async_client.py
supermetrics/client.py
supermetrics/exceptions.py
supermetrics/_generated/.gitignore
supermetrics/_generated/README.md
supermetrics/_generated/supermetrics_api_client/__init__.py
supermetrics/_generated/supermetrics_api_client/client.py
supermetrics/_generated/supermetrics_api_client/errors.py
supermetrics/_generated/supermetrics_api_client/py.typed
supermetrics/_generated/supermetrics_api_client/types.py
supermetrics/_generated/supermetrics_api_client/api/__init__.py
supermetrics/_generated/supermetrics_api_client/api/data_source/__init__.py
supermetrics/_generated/supermetrics_api_client/api/data_source/get_accounts.py
supermetrics/_generated/supermetrics_api_client/api/data_source_login_links/__init__.py
supermetrics/_generated/supermetrics_api_client/api/data_source_login_links/close_login_link.py
supermetrics/_generated/supermetrics_api_client/api/data_source_login_links/create_login_link.py
supermetrics/_generated/supermetrics_api_client/api/data_source_login_links/get_login_link.py
supermetrics/_generated/supermetrics_api_client/api/data_source_login_links/list_login_links.py
supermetrics/_generated/supermetrics_api_client/api/data_source_logins/__init__.py
supermetrics/_generated/supermetrics_api_client/api/data_source_logins/get_data_source_login.py
supermetrics/_generated/supermetrics_api_client/api/data_source_logins/list_data_source_logins.py
supermetrics/_generated/supermetrics_api_client/api/get_data/__init__.py
supermetrics/_generated/supermetrics_api_client/api/get_data/get_data.py
supermetrics/_generated/supermetrics_api_client/models/__init__.py
supermetrics/_generated/supermetrics_api_client/models/close_login_link_response_401.py
supermetrics/_generated/supermetrics_api_client/models/close_login_link_response_404.py
supermetrics/_generated/supermetrics_api_client/models/close_login_link_response_404_error.py
supermetrics-0.1.0b0.dist-info/METADATA
supermetrics-0.1.0b0.dist-info/WHEEL
supermetrics-0.1.0b0.dist-info/licenses/LICENSE
supermetrics-0.1.0b0.dist-info/RECORD
