Metadata-Version: 2.4
Name: supermetrics
Version: 0.1.0b0
Summary: Official Python client for Supermetrics
Project-URL: homepage, https://github.com/supermetrics-public/supermetrics-python-sdk
Project-URL: bugs, https://github.com/supermetrics-public/supermetrics-python-sdk/issues
Project-URL: changelog, https://github.com/supermetrics-public/supermetrics-python-sdk/blob/main/HISTORY.md
Author-email: Aleksei Popov <aleksei.popov@supermetrics.com>, Pablo Rojas <pablo.rojas@supermetrics.com>, Feroj Ahmod <feroj.ahmod@supermetrics.com>
Maintainer-email: Aleksei Popov <aleksei.popov@supermetrics.com>, Pablo Rojas <pablo.rojas@supermetrics.com>, Feroj Ahmod <feroj.ahmod@supermetrics.com>
License: Apache-2.0
License-File: LICENSE
Classifier: Development Status :: 3 - Alpha
Classifier: Intended Audience :: Developers
Classifier: License :: OSI Approved :: Apache Software License
Classifier: Programming Language :: Python :: 3
Classifier: Programming Language :: Python :: 3.11
Classifier: Programming Language :: Python :: 3.12
Classifier: Programming Language :: Python :: 3.13
Classifier: Programming Language :: Python :: 3.14
Requires-Python: >=3.11
Requires-Dist: attrs>=23.0.0
Requires-Dist: httpx>=0.25.0
Requires-Dist: pydantic>=2.0.0
Requires-Dist: python-dateutil>=2.8.0
Provides-Extra: dev
Requires-Dist: mypy>=1.7.0; extra == 'dev'
Requires-Dist: openapi-python-client>=0.15.0; extra == 'dev'
Requires-Dist: pytest-asyncio>=0.21.0; extra == 'dev'
Requires-Dist: pytest-cov>=4.1.0; extra == 'dev'
Requires-Dist: pytest>=7.4.0; extra == 'dev'
Requires-Dist: pyyaml>=6.0.0; extra == 'dev'
Requires-Dist: ruff>=0.1.0; extra == 'dev'
